cemm/__init__.py
cemm/cemm.py
cemm/exceptions.py
cemm/models.py
cemm/py.typed
cemm-0.5.1.dist-info/METADATA
cemm-0.5.1.dist-info/WHEEL
cemm-0.5.1.dist-info/LICENSE
cemm-0.5.1.dist-info/RECORD
